[{"budget":530506.0,"country":"CU","description":"","expenditure":11562.0,"implementer":"United Nations Office for Project Services","location":1,"locations":[{"coordinates":["-77.781166999999982000","21.521757000000001000"],"location-type":"PCL"}],"reporting":"United Nations Office for Project Services","sector":["Environmental policy and administrative management"],"title":"Global Environment Facility (GEF) Small Grants Programme, 5th Operational Phase"},{"budget":67578.0,"country":"CU","description":"","expenditure":809.0,"implementer":"UNDP","location":0,"locations":[{"coordinates":["-78.870313","21.929528"],"location-type":"PCL"}],"reporting":"United Nations Development Programme","sector":["Sectors Not Specified"],"title":"UN COORDINATION FOR RESULTS IN CUBA"},{"budget":0,"country":"CU","description":"","expenditure":0,"implementer":"World Food Programme","location":1,"locations":[{"coordinates":["-78.870313","21.929528"],"location-type":"PCL"}],"reporting":"World Food Programme","sector":["Emergency food aid"],"title":"Food Assistance in Response to Hurricanes Gustav and Ike"},{"budget":82567.0,"country":"CU","description":"","expenditure":82567.0,"implementer":"UNDP","location":1,"locations":[{"coordinates":["-78.870313","21.929528"],"location-type":"PCL"},{"coordinates":["-82.38304","23.13302"],"location-type":"PPLC"}],"reporting":"United Nations Development Programme","sector":["Sectors Not Specified"],"title":"Landscape Approach / Mountains (GEF)"},{"budget":0,"country":"CU","description":"","expenditure":0,"implementer":"UN POPULATION FUND","location":1,"locations":[{"coordinates":["-78.870313","21.929528"],"location-type":"PCL"}],"reporting":"United Nations Population Fund","sector":["Sectors Not Specified"],"title":"Revitalizar Servicios Salud Materna y de SSR"},{"budget":737120.0,"country":"CU","description":"","expenditure":721727.0,"implementer":"Ministerio Inversi\u00f3n Extranjer","location":1,"locations":[{"coordinates":["-78.870313","21.929528"],"location-type":"PCL"},{"coordinates":["-79.4425","21.92972"],"location-type":"PPLA"}],"reporting":"United Nations Development Programme","sector":["Sectors Not Specified"],"title":"MODERNIZACI\u00d3N SECTOR AGROPECUARIO CUBA"},{"budget":118953.0,"country":"CU","description":"","expenditure":106013.0,"implementer":"UNDP","location":1,"locations":[{"coordinates":["-78.870313","21.929528"],"location-type":"PCL"},{"coordinates":["-76.95111","20.96167"],"location-type":"PPLA"}],"reporting":"United Nations Development Programme","sector":["Sectors Not Specified"],"title":"Hydro meteorological & warning system"},{"budget":0,"country":"CU","description":"","expenditure":0,"implementer":"Ministerio Inversi\u00f3n Extranjer","location":0,"locations":[{"coordinates":["-78.870313","21.929528"],"location-type":"PCL"}],"reporting":"United Nations Development Programme","sector":["Sectors Not Specified"],"title":"AGROCADENAS"},{"budget":1770484.0,"country":"CU","description":"","expenditure":1583319.0,"implementer":"MINISTERIO DE LA CIENCIA, TECN","location":1,"locations":[{"coordinates":["-78.870313","21.929528"],"location-type":"PCL"},{"coordinates":["-77.82778","21.24278"],"location-type":"PPL"},{"coordinates":["-77.82778","21.24278"],"location-type":"PPL"}],"reporting":"United Nations Development Programme","sector":["Sectors Not Specified"],"title":"BASES AMBIENTALES PARA LA SOSTENIBILIDAD ALIMENTARIA"},{"budget":0,"country":"CU","description":"","expenditure":273950.0,"implementer":"","location":1,"locations":[{"coordinates":["-78.870313","21.929528"],"location-type":"PCL"}],"reporting":"UN Habitat","sector":["Sectors Not Specified"],"title":"Contribution To The Systematization Of Housing Recuperation Experience In 3 Provinces In Cuba"},{"budget":138326.0,"country":"CU","description":"","expenditure":-1288.0,"implementer":"United Nations Office for Project Services","location":1,"locations":[{"coordinates":["-82.388556999999992000","23.116800000000001000"],"location-type":"PPL"}],"reporting":"United Nations Office for Project Services","sector":["Waste management  and  disposal"],"title":"Demonstration of Innovative Approaches to the Rehabilitation of Heavily Contaminated Bays in the Wider Caribbean."},{"budget":757843.0,"country":"CU","description":"","expenditure":639978.0,"implementer":"Ministerio Inversi\u00f3n Extranjer","location":1,"locations":[{"coordinates":["-78.870313","21.929528"],"location-type":"PCL"},{"coordinates":["-79.5","22"],"location-type":"PCL"}],"reporting":"United Nations Development Programme","sector":["Sectors Not Specified"],"title":"Control Tuberculosis en Cuba (Fase II)"},{"budget":177959.0,"country":"CU","description":"","expenditure":126041.0,"implementer":"UNDP","location":1,"locations":[{"coordinates":["-78.870313","21.929528"],"location-type":"PCL"},{"coordinates":["-83.69806","22.4175"],"location-type":"PPLA"}],"reporting":"United Nations Development Programme","sector":["Sectors Not Specified"],"title":"CUBA: MONITORING SUSTAINABLE LAND MANAGEMENT PROGRAMME"},{"budget":4957826.0,"country":"CU","description":"","expenditure":5152959.0,"implementer":"UNDP","location":1,"locations":[{"coordinates":["-78.870313","21.929528"],"location-type":"PCL"},{"coordinates":["-79.5","22"],"location-type":"PCL"}],"reporting":"United Nations Development Programme","sector":["Sectors Not Specified"],"title":"Respuesta Nacional VIH/sida"},{"budget":89500.0,"country":"CU","description":"","expenditure":89192.0,"implementer":"UNDP","location":1,"locations":[{"coordinates":["-78.870313","21.929528"],"location-type":"PCL"},{"coordinates":["-75.82194","20.02472"],"location-type":"PPLA"}],"reporting":"United Nations Development Programme","sector":["Sectors Not Specified"],"title":"Recuperaci\u00f3n Resiliente Santiago de Cuba"},{"budget":1299449.0,"country":"CU","description":"","expenditure":1276033.0,"implementer":"UNDP","location":1,"locations":[{"coordinates":["-78.870313","21.929528"],"location-type":"PCL"},{"coordinates":["-79.5","22"],"location-type":"PCL"}],"reporting":"United Nations Development Programme","sector":["Sectors Not Specified"],"title":"CUBA MARINE & COASTAL PROTECTED AREAS"},{"budget":330465.0,"country":"CU","description":"","expenditure":26958.0,"implementer":"World Food Programme","location":1,"locations":[{"coordinates":["-78.870313","21.929528"],"location-type":"PCL"}],"reporting":"World Food Programme","sector":["Basic nutrition"],"title":"Support for the National Plan on the Prevention and Control of Anaemia in the Five Eastern Provinces of Cuba"},{"budget":0,"country":"CU","description":"","expenditure":240005.0,"implementer":"","location":1,"locations":[{"coordinates":["-78.870313","21.929528"],"location-type":"PCL"}],"reporting":"UN Habitat","sector":["Sectors Not Specified"],"title":"Support To Transformations Of The Housing Sector In Cuba"},{"budget":1392627.0,"country":"CU","description":"","expenditure":1347450.0,"implementer":"UNDP","location":1,"locations":[{"coordinates":["-78.870313","21.929528"],"location-type":"PCL"},{"coordinates":["-75.99889","20.21722"],"location-type":"PPL"}],"reporting":"United Nations Development Programme","sector":["Sectors Not Specified"],"title":"Reestablishing basic living conditions of families"},{"budget":70000.0,"country":"CU","description":"","expenditure":42599.0,"implementer":"MINISTERIO DE LA CIENCIA, TECN","location":1,"locations":[{"coordinates":["-78.870313","21.929528"],"location-type":"PCL"},{"coordinates":["-79.5","22"],"location-type":"PCL"},{"coordinates":["-82.38304","23.13302"],"location-type":"PPLC"}],"reporting":"United Nations Development Programme","sector":["Sectors Not Specified"],"title":"HCFC PHASE-OUT MANAGEMENT PLAN"},{"budget":831000.0,"country":"CU","description":"","expenditure":818237.0,"implementer":"UNDP","location":1,"locations":[{"coordinates":["-78.870313","21.929528"],"location-type":"PCL"},{"coordinates":["-83.69806","22.4175"],"location-type":"PPLA"}],"reporting":"United Nations Development Programme","sector":["Sectors Not Specified"],"title":"CUBA: SUSTAINABLE LAND MANAGEMENT IN DEGRADED ECOSYSTEMS"},{"budget":3000.0,"country":"CU","description":"","expenditure":2489.0,"implementer":"UNITED NATIONS DEVELOPMENT PRO","location":1,"locations":[{"coordinates":["-78.870313","21.929528"],"location-type":"PCL"},{"coordinates":["-81.5775","23.04111"],"location-type":"PPLA"}],"reporting":"United Nations Development Programme","sector":["Sectors Not Specified"],"title":"GEF-PIMS 4899 CLEAN ENERGY TECHNOLOGIES (PREPARATION)"},{"budget":220334.0,"country":"CU","description":"","expenditure":18684.0,"implementer":"United Nations Office for Project Services","location":1,"locations":[{"coordinates":["-77.781166999999982000","21.521757000000001000"],"location-type":"PCL"}],"reporting":"United Nations Office for Project Services","sector":["Environmental policy and administrative management"],"title":"Global Environment Facility (GEF) Small Grants Programme, 4th Operational Phase"},{"budget":0,"country":"CU","description":"","expenditure":378.0,"implementer":"World Food Programme","location":1,"locations":[{"coordinates":["-78.870313","21.929528"],"location-type":"PCL"}],"reporting":"World Food Programme","sector":["Emergency food aid"],"title":"IR-EMOP - Emergency Assistance to People Affected by Hurricane Sandy in Cuba"},{"budget":1150000.0,"country":"CU","description":"","expenditure":1157884.0,"implementer":"UNDP","location":1,"locations":[{"coordinates":["-78.870313","21.929528"],"location-type":"PCL"},{"coordinates":["-79.5","22"],"location-type":"PCL"}],"reporting":"United Nations Development Programme","sector":["Sectors Not Specified"],"title":"Cuba: Control and management of invasive alien species"},{"budget":1447284.0,"country":"CU","description":"","expenditure":176485.0,"implementer":"World Food Programme","location":1,"locations":[{"coordinates":["-78.870313","21.929528"],"location-type":"PCL"}],"reporting":"World Food Programme","sector":["Emergency food aid"],"title":"Emergency Assistance to People Affected in Cuba by Hurricane  Sandy in the provinces of Santiago de Cuba,Holguin and Guantanamo"},{"budget":219100.0,"country":"CU","description":"","expenditure":59068.0,"implementer":"Ministerio Inversi\u00f3n Extranjer","location":1,"locations":[{"coordinates":["-78.870313","21.929528"],"location-type":"PCL"},{"coordinates":["-82.38304","23.13302"],"location-type":"PPLC"}],"reporting":"United Nations Development Programme","sector":["Sectors Not Specified"],"title":"Mejora habitat rural en marco estrategia agroalimentaria"},{"budget":975000.0,"country":"CU","description":"","expenditure":954221.0,"implementer":"UNDP","location":1,"locations":[{"coordinates":["-78.870313","21.929528"],"location-type":"PCL"},{"coordinates":["-79","22.5"],"location-type":"ADM1"}],"reporting":"United Nations Development Programme","sector":["Sectors Not Specified"],"title":"Biodiversity Conservation in Sabana Camaguey Ecosystem"},{"budget":105853.0,"country":"CU","description":"","expenditure":104755.0,"implementer":"Ministerio Inversi\u00f3n Extranjer","location":1,"locations":[{"coordinates":["-78.870313","21.929528"],"location-type":"PCL"},{"coordinates":["-76.76222","20.86667"],"location-type":"PPL"}],"reporting":"United Nations Development Programme","sector":["Sectors Not Specified"],"title":"Cuba: Segunda Comunicaci\u00f3n Nacional Cambio Clim\u00e1tico"},{"budget":56525.0,"country":"CU","description":"","expenditure":53322.0,"implementer":"Ministerio Inversi\u00f3n Extranjer","location":1,"locations":[{"coordinates":["-78.870313","21.929528"],"location-type":"PCL"},{"coordinates":["-83.69806","22.4175"],"location-type":"PPLA"}],"reporting":"United Nations Development Programme","sector":["Sectors Not Specified"],"title":"PROGRAMA MARCO DESARROLLO HUMANO LOCAL PDHL 2008-12"},{"budget":1047854.0,"country":"CU","description":"","expenditure":1045898.0,"implementer":"Ministerio Inversi\u00f3n Extranjer","location":1,"locations":[{"coordinates":["-78.870313","21.929528"],"location-type":"PCL"},{"coordinates":["-83.69806","22.4175"],"location-type":"PPLA"}],"reporting":"United Nations Development Programme","sector":["Sectors Not Specified"],"title":"ODM- APOYO A LAS INICIATIVAS DE DESCENTRALIZACI\u00d3N CUBA"},{"budget":268782.0,"country":"CU","description":"","expenditure":71409.0,"implementer":"UNDP","location":1,"locations":[{"coordinates":["-78.870313","21.929528"],"location-type":"PCL"},{"coordinates":["-79.5","22"],"location-type":"PCL"}],"reporting":"United Nations Development Programme","sector":["Sectors Not Specified"],"title":"BASIC LIVING CONDITIONS"},{"budget":69200.0,"country":"CU","description":"","expenditure":69159.0,"implementer":"MINISTERIO DE LA CIENCIA, TECN","location":1,"locations":[{"coordinates":["-78.870313","21.929528"],"location-type":"PCL"},{"coordinates":["-82.39197","23.11936"],"location-type":"PPL"}],"reporting":"United Nations Development Programme","sector":["Sectors Not Specified"],"title":"Fortalecimiento Institucional OTOZ VIII"},{"budget":233185.0,"country":"CU","description":"","expenditure":233158.0,"implementer":"MINISTERIO DE LA CIENCIA, TECN","location":1,"locations":[{"coordinates":["-78.870313","21.929528"],"location-type":"PCL"},{"coordinates":["-79.30194","21.99806"],"location-type":"PPL"}],"reporting":"United Nations Development Programme","sector":["Sectors Not Specified"],"title":"DESTRUCCION SUSTANCIAS AGOTADORAS DEL OZONO"}]